run_parallel/__init__.py
run_parallel/run_parallel.py
run_parallel-0.0.6.dist-info/LICENSE
run_parallel-0.0.6.dist-info/METADATA
run_parallel-0.0.6.dist-info/WHEEL
run_parallel-0.0.6.dist-info/top_level.txt
run_parallel-0.0.6.dist-info/RECORD
