Metadata-Version: 2.1
Name: run-parallel
Version: 0.0.6
Summary: Pass an array or generator of callables and `run_parallel` will run them as fast as possible.
Home-page: https://github.com/tom-010/run_parallel
Author: Thomas Deniffel
Author-email: tdeniffel@gmail.com
License: Apache2
Platform: UNKNOWN
Classifier: Development Status :: 4 - Beta
Classifier: Intended Audience :: Developers
Classifier: Programming Language :: Python
Classifier: Programming Language :: Python :: 3 :: Only
Classifier: Programming Language :: Python :: 3.6
Classifier: Programming Language :: Python :: 3.7
Requires-Python: >=3
License-File: LICENSE
